mcp_sharepoint/__init__.py
mcp_sharepoint/__main__.py
mcp_sharepoint/auth.py
mcp_sharepoint/graph_api.py
mcp_sharepoint_us-2.0.16.dist-info/licenses/LICENSE
mcp_sharepoint_us-2.0.16.dist-info/METADATA
mcp_sharepoint_us-2.0.16.dist-info/WHEEL
mcp_sharepoint_us-2.0.16.dist-info/entry_points.txt
mcp_sharepoint_us-2.0.16.dist-info/top_level.txt
mcp_sharepoint_us-2.0.16.dist-info/RECORD
