Metadata-Version: 2.4
Name: mcp-sharepoint-us
Version: 2.0.16
Summary: SharePoint MCP Server with Microsoft Graph API
License: MIT
Project-URL: Homepage, https://github.com/mdev26/mcp-sharepoint-us
Project-URL: Repository, https://github.com/mdev26/mcp-sharepoint-us
Project-URL: Bug Tracker, https://github.com/mdev26/mcp-sharepoint-us/issues
Keywords: mcp,sharepoint,microsoft,azure,office365,msal
Classifier: Development Status :: 4 - Beta
Classifier: Intended Audience :: Developers
Classifier: License :: OSI Approved :: MIT License
Classifier: Programming Language :: Python :: 3
Classifier: Programming Language :: Python :: 3.10
Classifier: Programming Language :: Python :: 3.11
Classifier: Programming Language :: Python :: 3.12
Requires-Python: >=3.10
License-File: LICENSE
Requires-Dist: mcp>=1.0.0
Requires-Dist: office365-rest-python-client>=2.5.0
Requires-Dist: msal>=1.24.0
Requires-Dist: python-dotenv>=1.0.0
Requires-Dist: pydantic>=2.0.0
Requires-Dist: requests>=2.31.0
Provides-Extra: dev
Requires-Dist: pytest>=7.0.0; extra == "dev"
Requires-Dist: pytest-asyncio>=0.21.0; extra == "dev"
Requires-Dist: black>=23.0.0; extra == "dev"
Requires-Dist: ruff>=0.1.0; extra == "dev"
Dynamic: license-file
